{"id":"sm10-198","name":"Marshadow & Machamp-GX","supertype":"Pokémon","subtypes":["Basic","TAG TEAM","GX"],"hp":"270","types":["Fighting"],"rules":["TAG TEAM rule: When your TAG TEAM is Knocked Out, your opponent takes 3 Prize cards."],"attacks":[{"name":"Revenge","cost":["Fighting","Colorless"],"convertedEnergyCost":2,"damage":"30+","text":"If any of your Pokémon were Knocked Out by damage from an opponent's attack during their last turn, this attack does 90 more damage."},{"name":"Hundred-Blows Impact","cost":["Fighting","Fighting","Colorless"],"convertedEnergyCost":3,"damage":"160","text":""},{"name":"Acme of Heroism-GX","cost":["Fighting","Fighting","Colorless"],"convertedEnergyCost":3,"damage":"200","text":"If this Pokémon has at least 1 extra Energy attached to it (in addition to this attack's cost), and if it would be Knocked Out by damage from an opponent's attack during their next turn, it is not Knocked Out, and its remaining HP becomes 10. (You can't use more than 1 GX attack in a game.)"}],"weaknesses":[{"type":"Psychic","value":"×2"}],"retreatCost":["Colorless","Colorless","Colorless"],"convertedRetreatCost":3,"set":{"id":"sm10","name":"Unbroken Bonds","series":"Sun & Moon","printedTotal":214,"total":234,"legalities":{"unlimited":"Legal","expanded":"Legal"},"ptcgoCode":"UNB","releaseDate":"2019/05/03","updatedAt":"2021/09/01 05:37:00","images":{"symbol":"https://images.pokemontcg.io/sm10/symbol.png","logo":"https://images.pokemontcg.io/sm10/logo.png"}},"number":"198","artist":"5ban Graphics","rarity":"Rare Ultra","nationalPokedexNumbers":[68,802],"legalities":{"unlimited":"Legal","expanded":"Legal"},"images":{"small":"https://images.pokemontcg.io/sm10/198.png","large":"https://images.pokemontcg.io/sm10/198_hires.png"},"tcgplayer":{"url":"https://prices.pokemontcg.io/tcgplayer/sm10-198","updatedAt":"2023/09/15","prices":{"holofoil":{"low":11.5,"mid":16.61,"high":43.14,"market":15.07,"directLow":43.13}}},"cardmarket":{"url":"https://prices.pokemontcg.io/cardmarket/sm10-198","updatedAt":"2023/09/15","prices":{"averageSellPrice":13.9,"lowPrice":4.0,"trendPrice":12.54,"germanProLow":0.0,"suggestedPrice":0.0,"reverseHoloSell":0.0,"reverseHoloLow":0.0,"reverseHoloTrend":10.53,"lowPriceExPlus":9.5,"avg1":13.9,"avg7":11.2,"avg30":10.19,"reverseHoloAvg1":11.52,"reverseHoloAvg7":11.31,"reverseHoloAvg30":8.77}}}